dltx/__init__.py
dltx/dltx.py
dltx-0.1.1.dist-info/LICENCE
dltx-0.1.1.dist-info/METADATA
dltx-0.1.1.dist-info/WHEEL
dltx-0.1.1.dist-info/top_level.txt
dltx-0.1.1.dist-info/RECORD
