Metadata-Version: 2.1
Name: dltx
Version: 0.1.1
Summary: Direct Linear Transform (DLT)
Home-page: https://github.com/joonaojapalo/dltx
Author: Marcos Duarte
Author-email: duartexyz@gmail.com
Maintainer: Joona Ojapalo
Maintainer-email: joona.ojapalo@iki.fi
License: Attribution 4.0 International
License-File: LICENCE
Requires-Dist: numpy
